vllm/__init__.py
vllm/activation_ops.cpython-310-x86_64-linux-gnu.so
vllm/attention_ops.cpython-310-x86_64-linux-gnu.so
vllm/block.py
vllm/cache_ops.cpython-310-x86_64-linux-gnu.so
vllm/config.py
vllm/cuda_utils.cpython-310-x86_64-linux-gnu.so
vllm/layernorm_ops.cpython-310-x86_64-linux-gnu.so
vllm/logger.py
vllm/outputs.py
vllm/pos_encoding_ops.cpython-310-x86_64-linux-gnu.so
vllm/quantization_ops.cpython-310-x86_64-linux-gnu.so
vllm/sampling_params.py
vllm/sequence.py
vllm/utils.py
vllm/core/__init__.py
vllm/core/block_manager.py
vllm/core/policy.py
vllm/core/scheduler.py
vllm/engine/__init__.py
vllm/engine/arg_utils.py
vllm/engine/async_llm_engine.py
vllm/engine/llm_engine.py
vllm/engine/ray_utils.py
vllm/entrypoints/__init__.py
vllm/entrypoints/api_server.py
vllm/entrypoints/consul_registry.py
vllm/entrypoints/llm.py
vllm/entrypoints/openai/__init__.py
vllm/entrypoints/openai/api_server.py
vllm/entrypoints/openai/protocol.py
vllm/model_executor/__init__.py
vllm/model_executor/input_metadata.py
vllm/model_executor/model_loader.py
vllm/model_executor/utils.py
vllm/model_executor/weight_utils.py
vllm/model_executor/layers/__init__.py
vllm/model_executor/layers/activation.py
vllm/model_executor/layers/attention.py
vllm/model_executor/layers/layernorm.py
vllm/model_executor/layers/rotary_embedding.py
vllm/model_executor/layers/sampler.py
vllm/model_executor/layers/quantized_linear/__init__.py
vllm/model_executor/layers/quantized_linear/awq.py
vllm/model_executor/layers/quantized_linear/squeezellm.py
vllm/model_executor/models/__init__.py
vllm/model_executor/models/aquila.py
vllm/model_executor/models/baichuan.py
vllm/model_executor/models/bloom.py
vllm/model_executor/models/falcon.py
vllm/model_executor/models/gpt2.py
vllm/model_executor/models/gpt_bigcode.py
vllm/model_executor/models/gpt_j.py
vllm/model_executor/models/gpt_neox.py
vllm/model_executor/models/internlm.py
vllm/model_executor/models/llama.py
vllm/model_executor/models/mistral.py
vllm_consul-0.2.1.dist-info/LICENSE
vllm_consul-0.2.1.dist-info/METADATA
vllm_consul-0.2.1.dist-info/WHEEL
vllm_consul-0.2.1.dist-info/top_level.txt
vllm_consul-0.2.1.dist-info/RECORD
